htmlview/HTMLMaker.py
htmlview/__init__.py
sierralocal/__init__.py
sierralocal/hivdb.py
sierralocal/jsonwriter.py
sierralocal/main.py
sierralocal/nucaminohook.py
sierralocal/score_alg.py
sierralocal/updater.py
sierralocal/utils.py
sierralocal/bin/minimap2
sierralocal/bin/minimap2.darwin
sierralocal/bin/minimap2.linux
sierralocal/bin/nucamino-darwin-386
sierralocal/bin/nucamino-darwin-amd64
sierralocal/bin/nucamino-linux-386
sierralocal/bin/nucamino-linux-amd64
sierralocal/bin/nucamino-windows-386.exe
sierralocal/bin/nucamino-windows-amd64.exe
sierralocal/bin/postalign
sierralocal/bin/postalign.darwin
sierralocal/bin/postalign.linux
sierralocal/data/HIVDB_9.4.xml
sierralocal/data/INIPrevalences.tsv
sierralocal/data/INSTI-comments.csv
sierralocal/data/PI-comments.csv
sierralocal/data/PIPrevalences.tsv
sierralocal/data/RT-comments.csv
sierralocal/data/RTIPrevalences.tsv
sierralocal/data/alignment-config_hiv1.json
sierralocal/data/apobec_drms.json
sierralocal/data/apobecs.csv
sierralocal/data/mutation-type-pairs_hiv1.csv
sierralocal/data/rx-all_subtype-all.csv
sierralocal/data/sdrms_hiv1.csv
sierralocal-0.4.3.data/scripts/sierralocal
sierralocal-0.4.3.dist-info/licenses/AUTHORS
sierralocal-0.4.3.dist-info/licenses/LICENSE
sierralocal-0.4.3.dist-info/METADATA
sierralocal-0.4.3.dist-info/WHEEL
sierralocal-0.4.3.dist-info/top_level.txt
sierralocal-0.4.3.dist-info/RECORD
