Metadata-Version: 2.4
Name: sierralocal
Version: 0.4.3
Summary: Local execution of HIVdb algorithm
Home-page: https://github.com/PoonLab/sierra-local
Author: ['Jasper Ho', 'Garway Ng', 'Gopi Gugan', 'Mathias Renaud', 'William Wang', 'Art Poon']
Author-email: ['jasperchho@gmail.com', 'apoon42@uwo.ca']
Classifier: Programming Language :: Python :: 3
Classifier: License :: OSI Approved :: GNU General Public License v3 (GPLv3)
Classifier: Operating System :: OS Independent
License-File: LICENSE
License-File: AUTHORS
Requires-Dist: cython>=0.29.35
Requires-Dist: more-itertools>=9.1.0
Requires-Dist: orjson>=3.9.1
Requires-Dist: types-setuptools>=67.8.0.0
Dynamic: author
Dynamic: author-email
Dynamic: classifier
Dynamic: description
Dynamic: home-page
Dynamic: license-file
Dynamic: requires-dist
Dynamic: summary
